<?xml version='1.0' encoding='utf-8'?>
<snippets language="diff">
  <snippet>
    <text><![CDATA[grammar: ${1:s///}]]></text>
    <tag>gmr</tag>
    <description>grammar</description>
  </snippet>
  <snippet>
    <text><![CDATA[I see trailing whitespace.]]></text>
    <tag>tw</tag>
    <description>trailing whitespace</description>
  </snippet>
  <snippet>
    <text><![CDATA[Wrap the narrative at 72 characters.]]></text>
    <tag>wn</tag>
    <description>wrap narrative</description>
  </snippet>
  <snippet>
    <text><![CDATA[Wrap the code at 78 characters.]]></text>
    <tag>wc</tag>
    <description>wrap code</description>
  </snippet>
</snippets>
